units/__init__.py
units/banner.py
units/chnet.py
units/urls.py
openredirectscanner-0.1.3.dist-info/METADATA
openredirectscanner-0.1.3.dist-info/WHEEL
openredirectscanner-0.1.3.dist-info/entry_points.txt
openredirectscanner-0.1.3.dist-info/top_level.txt
openredirectscanner-0.1.3.dist-info/RECORD
