Metadata-Version: 2.1
Name: openredirectscanner
Version: 0.1.3
Summary: Open Redirect Bug Finding Tool
Author: Snega Prabhavathi
Author-email: prabhavathisnega@gmail.com
Classifier: Development Status :: 3 - Alpha
Classifier: Intended Audience :: Developers
Classifier: Topic :: Software Development :: Libraries :: Python Modules
Classifier: Programming Language :: Python :: 3
Classifier: Programming Language :: Python :: 3.7
Classifier: Programming Language :: Python :: 3.8
Classifier: Programming Language :: Python :: 3.9
Classifier: Programming Language :: Python :: 3.10
Classifier: Programming Language :: Python :: 3.11
Classifier: Programming Language :: Python :: 3.12
Requires-Dist: requests >=2.25.1
Requires-Dist: argparse >=1.4.0
Requires-Dist: termcolor >=1.1.0
Requires-Dist: pyfiglet >=0.8.post1
